ml_graphy-0.1.1.dist-info/licenses/LICENSE
mlgraphy/__init__.py
mlgraphy/plotting.py
ml_graphy-0.1.1.dist-info/METADATA
ml_graphy-0.1.1.dist-info/WHEEL
ml_graphy-0.1.1.dist-info/top_level.txt
ml_graphy-0.1.1.dist-info/RECORD
