Metadata-Version: 2.4
Name: ml-graphy
Version: 0.1.1
Summary: A Python package for plotting machine learning training metrics
Author-email: Prasoon Rai <prasoonrai@icloud.com>
License: MIT
Project-URL: Homepage, https://github.com/Prasoon-Rai/ml-graphy
Project-URL: Bug Reports, https://github.com/Prasoon-Rai/ml-graphy/issues
Project-URL: Source, https://github.com/Prasoon-Rai/ml-graphy
Keywords: machine learning,deep learning,plotting,metrics,visualization
Classifier: Development Status :: 3 - Alpha
Classifier: Intended Audience :: Developers
Classifier: License :: OSI Approved :: MIT License
Classifier: Programming Language :: Python :: 3
Classifier: Programming Language :: Python :: 3.8
Classifier: Programming Language :: Python :: 3.9
Classifier: Programming Language :: Python :: 3.10
Classifier: Programming Language :: Python :: 3.11
Classifier: Programming Language :: Python :: 3.12
Requires-Python: >=3.8
License-File: LICENSE
Requires-Dist: numpy>=1.20.0
Requires-Dist: matplotlib>=3.5.0
Requires-Dist: seaborn>=0.11.0
Provides-Extra: dev
Requires-Dist: pytest>=7.0; extra == "dev"
Requires-Dist: black>=22.0; extra == "dev"
Requires-Dist: flake8>=4.0; extra == "dev"
Requires-Dist: mypy>=0.950; extra == "dev"
Dynamic: license-file
